designed/__init__.py
designed/en/__init__.py
designed/en/__init__.pyi
designed/en/python_version_3_10/__init__.py
designed/en/python_version_3_10/pyarmor_runtime_004089/__init__.py
designed/en/python_version_3_10/pyarmor_runtime_004089/darwin_universal/pyarmor_runtime.so
designed/en/python_version_3_10/pyarmor_runtime_004089/linux_x86_64/pyarmor_runtime.so
designed/en/python_version_3_10/pyarmor_runtime_004089/windows_x86_64/pyarmor_runtime.pyd
designed/en/python_version_3_10/src/__init__.py
designed/en/python_version_3_10/src/__singleton.py
designed/en/python_version_3_10/src/_ad.py
designed/en/python_version_3_10/src/ast.py
designed/en/python_version_3_10/src/ax.py
designed/en/python_version_3_10/src/complex_condition.py
designed/en/python_version_3_10/src/conditional.py
designed/en/python_version_3_10/src/define_type.py
designed/en/python_version_3_10/src/define_type_mock.py
designed/en/python_version_3_10/src/define_type_mock_ad.py
designed/en/python_version_3_10/src/designed_float.py
designed/en/python_version_3_10/src/designed_range.py
designed/en/python_version_3_10/src/designed_set.py
designed/en/python_version_3_10/src/diophantine_equation_utils.py
designed/en/python_version_3_10/src/equation.py
designed/en/python_version_3_10/src/equation_utils.py
designed/en/python_version_3_10/src/equations.py
designed/en/python_version_3_10/src/figure.py
designed/en/python_version_3_10/src/figure_reservation.py
designed/en/python_version_3_10/src/formula.py
designed/en/python_version_3_10/src/formula_utils.py
designed/en/python_version_3_10/src/fraction.py
designed/en/python_version_3_10/src/inequation.py
designed/en/python_version_3_10/src/integer.py
designed/en/python_version_3_10/src/integer_utils.py
designed/en/python_version_3_10/src/intersect.py
designed/en/python_version_3_10/src/markdown_contents.py
designed/en/python_version_3_10/src/math_conditional.py
designed/en/python_version_3_10/src/math_markdown_sign.py
designed-0.0.1a22.dist-info/LICENSE
designed-0.0.1a22.dist-info/METADATA
designed-0.0.1a22.dist-info/WHEEL
designed-0.0.1a22.dist-info/top_level.txt
designed-0.0.1a22.dist-info/RECORD
