Metadata-Version: 2.1
Name: designed
Version: 0.0.1a22
Summary: Module for Supporting the Creation of University Entrance Examination Mathematics Proofs Using a Symbolic Computation Module
Home-page: https://github.com/chisakiShinichirouToshiyuki/designed
Author: chisakiShinichrouToshiyuki
Author-email: designed.academy@gmail.com
Classifier: Programming Language :: Python :: 3
Classifier: Operating System :: OS Independent
Requires-Python: >=3.8.0, <3.12.0
License-File: LICENSE
Requires-Dist: sympy ==1.11.*
Requires-Dist: jedi >=0.16
Requires-Dist: setuptools >65.5.1
Requires-Dist: spb ==0.1.*
Requires-Dist: seaborn ==0.12.*
Requires-Dist: japanize-matplotlib >=1.1.0
Requires-Dist: colorama ==0.4.*
Requires-Dist: matplotlib-venn >=0.11.10
